yaq_traits/VERSION
yaq_traits/__init__.py
yaq_traits/__main__.py
yaq_traits/__traits__.py
yaq_traits/__version__.py
yaq_traits/_check.py
yaq_traits/_compose.py
yaq_traits/has-dependents.toml
yaq_traits/has-limits.toml
yaq_traits/has-mapping.toml
yaq_traits/has-measure-trigger.toml
yaq_traits/has-position.toml
yaq_traits/has-transformed-position.toml
yaq_traits/has-turret.toml
yaq_traits/is-daemon.toml
yaq_traits/is-discrete.toml
yaq_traits/is-homeable.toml
yaq_traits/is-sensor.toml
yaq_traits/uses-i2c.toml
yaq_traits/uses-serial.toml
yaq_traits/uses-uart.toml
yaq_traits-2023.6.0.dist-info/entry_points.txt
yaq_traits-2023.6.0.dist-info/LICENSE
yaq_traits-2023.6.0.dist-info/WHEEL
yaq_traits-2023.6.0.dist-info/METADATA
yaq_traits-2023.6.0.dist-info/RECORD
