Metadata-Version: 2.1
Name: yaq-traits
Version: 2023.6.0
Summary: package defining yaq traits
Home-page: https://traits.yaq.fyi
Author: yaq Developers
Requires-Python: >=3.6
Classifier: Development Status :: 5 - Production/Stable
Classifier: Intended Audience :: Science/Research
Classifier: License :: OSI Approved :: GNU Lesser General Public License v3 (LGPLv3)
Classifier: Natural Language :: English
Classifier: Programming Language :: Python :: 3
Classifier: Programming Language :: Python :: 3.8
Classifier: Programming Language :: Python :: 3.9
Classifier: Programming Language :: Python :: 3.10
Classifier: Topic :: Scientific/Engineering
Requires-Dist: fastavro>=1.4.0
Requires-Dist: toml
Requires-Dist: click
Requires-Dist: prettytable
Requires-Dist: colorama
Requires-Dist: black ; extra == "dev"
Requires-Dist: pre-commit ; extra == "dev"
Project-URL: Issues, https://github.com/yaq-project/yaq-traits/issues
Project-URL: Source, https://github.com/yaq-project/yaq-traits
Provides-Extra: dev
